simodin/__init__.py
simodin/interface.py
simodin/extractors/__init__.py
simodin/extractors/dwsim.py
simodin/extractors/tespy.py
simodin-0.0.6.dist-info/licenses/LICENSE.txt
simodin-0.0.6.dist-info/METADATA
simodin-0.0.6.dist-info/WHEEL
simodin-0.0.6.dist-info/top_level.txt
simodin-0.0.6.dist-info/RECORD
