Metadata-Version: 2.4
Name: simodin
Version: 0.0.6
Summary: Interface between simulation models and brightway25
Home-page: https://github.com/HaSchneider/SiModIn
Author: Hannes Schneider
Author-email: simodin@posteo.de
License: MIT
Project-URL: Source, https://github.com/HaSchneider/SiModIn
Platform: any
Classifier: Development Status :: 4 - Beta
Classifier: Programming Language :: Python
Requires-Python: >=3.10
License-File: LICENSE.txt
Requires-Dist: pydantic
Requires-Dist: bw2calc>=2.0.1
Requires-Dist: bw2data>=4.4
Requires-Dist: pint
Requires-Dist: tespy>=0.9.4
Provides-Extra: testing
Requires-Dist: setuptools; extra == "testing"
Requires-Dist: pytest; extra == "testing"
Requires-Dist: pytest-cov; extra == "testing"
Dynamic: license-file
